pybpod_gui_plugin_trial_timeline-1.0.0.dist-info/METADATA
pybpod_gui_plugin_trial_timeline-1.0.0.dist-info/RECORD
pybpod_gui_plugin_trial_timeline-1.0.0.dist-info/WHEEL
pybpod_gui_plugin_trial_timeline-1.0.0.dist-info/top_level.txt
pybpodgui_plugin_trial_timeline/__init__.py
pybpodgui_plugin_trial_timeline/settings.py
pybpodgui_plugin_trial_timeline/trial_timeline.py
pybpodgui_plugin_trial_timeline/models/__init__.py
pybpodgui_plugin_trial_timeline/models/session/__init__.py
pybpodgui_plugin_trial_timeline/models/session/session_treenode.py
pybpodgui_plugin_trial_timeline/models/subject/__init__.py
pybpodgui_plugin_trial_timeline/models/subject/subject_treenode.py
