Metadata-Version: 2.1
Name: pybpod-gui-plugin-trial-timeline
Version: 1.0.0
Summary: PyBpod GUI Trial Timeline Plugin
Home-page: https://bitbucket.org/fchampalimaud/pybpod-gui-plugin-trial-timeline/
Author: Sérgio Copeto
Author-email: sergio.copeto@research.fchampalimaud.org
License: Copyright (C) 2007 Free Software Foundation, Inc. <http://fsf.org/>
Platform: UNKNOWN
